Workbook
Name Salary: APP!$C$10
Name InvestPct: APP!$C$11
Name Profile: APP!$C$13
Name Reinvest: APP!$C$14
Name Initial: APP!$C$17
Name Monthly: APP!$C$18
Name Horizon: APP!$C$19
Name Yield_m: APP!$C$20
Name Growth_m: APP!$C$21
Name Inflation_a: APP!$C$22
Name DeltaYield: BASE!$F$4
Name DeltaGrowth: BASE!$F$5
Name Discount_m: BASE!$F$6

Sheet APP
B2: DIO INVEST PRO — Simulador Premium de Fundos Imobiliários
B7: Insira seus parâmetros (em azul) e analise patrimônio, dividendos e cenários.
B9: CONFIGURAÇÕES | F9: RESULTADOS (PARA O PRAZO SELECIONADO)
B10: Salário mensal (R$) | C10: 2000 | F10: Total investido | K10: =Initial + Monthly*Horizon
B11: Renda % sugerida p/ investir | C11: 0.3 | F11: Patrimônio final | K11: =INDEX(ENGINE!$H$5:$H$365, Horizon+1)
B12: Sugestão de investimento (R$) | C12: =C10*C11 | F12: Dividendos no último mês | K12: =INDEX(ENGINE!$E$5:$E$365, Horizon+1)
B13: Perfil do investidor | C13: Moderado | F13: Dividendos sacados acumulados | K13: =INDEX(ENGINE!$I$5:$I$365, Horizon+1)
B14: Reinvestir dividendos? | C14: Sim | F14: Riqueza total final (Patrimônio + Dividendos) | K14: =INDEX(ENGINE!$J$5:$J$365, Horizon+1)
B16: INVESTIMENTO | F16: MÉTRICAS
B17: Valor inicial (R$) | C17: 0 | F17: TIR mensal (IRR) | K17: =IRR(ENGINE!$K$5:INDEX(ENGINE!$K$5:$K$365,Horizon+1))
B18: Aporte mensal (R$) | C18: 200 | F18: TIR anualizada | K18: =POWER(1+K17,12)-1
B19: Prazo (meses) | C19: 60 | F19: Patrimônio real (ajustado inflação) | K19: =K11/POWER(1+Inflation_a,Horizon/12)
B20: Dividend Yield mensal | C20: 0.0108 | F20: CAGR nominal (riqueza total) | K20: =POWER(K14/K10,12/Horizon)-1
B21: Crescimento da cota (mensal) | C21: 0.002 | F21: VPL (taxa desc. mensal em BASE) | K21: =NPV(Discount_m,ENGINE!$K$6:INDEX(ENGINE!$K$6:$K$365,Horizon)) + ENGINE!$K$5
B22: Inflação anual (opcional) | C22: 0.045
B25: PROJEÇÕES RÁPIDAS (MESMO APORTE) | F25: ALOCAÇÃO SUGERIDA POR TIPO DE FII (POR PERFIL)
B26: Horizonte | C26: Patrimônio | D26: Dividendo/mês | F26: Tipo | I26: % | K26: R$/mês
B27: 2 anos | C27: =INDEX(ENGINE!$H$5:$H$365,24+1) | D27: =INDEX(ENGINE!$E$5:$E$365,24+1) | F27: PAPEL | I27: =SUMIFS(BASE!$D:$D,BASE!$B:$B,Profile,BASE!$C:$C,F27) | K27: =C18*I27
B28: 5 anos | C28: =INDEX(ENGINE!$H$5:$H$365,60+1) | D28: =INDEX(ENGINE!$E$5:$E$365,60+1) | F28: TIJOLO | I28: =SUMIFS(BASE!$D:$D,BASE!$B:$B,Profile,BASE!$C:$C,F28) | K28: =C18*I28
B29: 10 anos | C29: =INDEX(ENGINE!$H$5:$H$365,120+1) | D29: =INDEX(ENGINE!$E$5:$E$365,120+1) | F29: HÍBRIDOS | I29: =SUMIFS(BASE!$D:$D,BASE!$B:$B,Profile,BASE!$C:$C,F29) | K29: =C18*I29
B30: 20 anos | C30: =INDEX(ENGINE!$H$5:$H$365,240+1) | D30: =INDEX(ENGINE!$E$5:$E$365,240+1) | F30: FOFs | I30: =SUMIFS(BASE!$D:$D,BASE!$B:$B,Profile,BASE!$C:$C,F30) | K30: =C18*I30
B31: 30 anos | C31: =INDEX(ENGINE!$H$5:$H$365,360+1) | D31: =INDEX(ENGINE!$E$5:$E$365,360+1) | F31: DESENVOLVIMENTO | I31: =SUMIFS(BASE!$D:$D,BASE!$B:$B,Profile,BASE!$C:$C,F31) | K31: =C18*I31
F32: HOTELARIAS | I32: =SUMIFS(BASE!$D:$D,BASE!$B:$B,Profile,BASE!$C:$C,F32) | K32: =C18*I32
F33: TOTAL | I33: =SUM(I27:I32) | K33: =SUM(K27:K32)

Sheet BASE
A1: TABELAS BASE (não editar)
A3: CHAVE | B3: PERFIL | C3: TIPO DE FII | D3: % | E3: PARÂMETROS DE CENÁRIO
A4: Conservador-PAPEL | B4: Conservador | C4: PAPEL | E4: Δ Dividend Yield (mensal) | F4: 0.002
A5: Conservador-TIJOLO | B5: Conservador | C5: TIJOLO | D5: 0.5 | E5: Δ Crescimento da cota (mensal) | F5: 0.001
A6: Conservador-HÍBRIDOS | B6: Conservador | C6: HÍBRIDOS | D6: 0.1 | E6: Taxa de desconto (mensal) p/ VPL | F6: 0.008
A7: Conservador-FOFs | B7: Conservador | C7: FOFs | D7: 0.1
A8: Conservador-DESENVOLVIMENTO | B8: Conservador | C8: DESENVOLVIMENTO | D8: 0
A9: Conservador-HOTELARIAS | B9: Conservador | C9: HOTELARIAS | D9: 0
A10: Moderado-PAPEL | B10: Moderado | C10: PAPEL | D10: 0.32
A11: Moderado-TIJOLO | B11: Moderado | C11: TIJOLO | D11: 0.35
A12: Moderado-HÍBRIDOS | B12: Moderado | C12: HÍBRIDOS | D12: 0.08
A13: Moderado-FOFs | B13: Moderado | C13: FOFs | D13: 0.05
A14: Moderado-DESENVOLVIMENTO | B14: Moderado | C14: DESENVOLVIMENTO | D14: 0.1
A15: Moderado-HOTELARIAS | B15: Moderado | C15: HOTELARIAS | D15: 0.1
A16: Agressivo-PAPEL | B16: Agressivo | C16: PAPEL | D16: 0.5
A17: Agressivo-TIJOLO | B17: Agressivo | C17: TIJOLO | D17: 0.1
A18: Agressivo-HÍBRIDOS | B18: Agressivo | C18: HÍBRIDOS | D18: 0.05
... A21: Agressivo-HOTELARIAS | B21: Agressivo | C21: HOTELARIAS | D21: 0.1

Sheet ENGINE
A1: ENGINE — Projeção mensal (0 a 360 meses). Não edite fórmulas.
A4: Mês | B4: Capital Base | C4: Saldo Inicial | D4: Aporte | E4: Dividendos | F4: Reinvestido | G4: Cresc. Cota | H4: Saldo Final | I4: Div. Sacados Acum. | J4: Riqueza Total | K4: Fluxo p/ TIR
A5: 0 | B5: =C{r}+D{r} | C5: =Initial | D5: 0 | E5: 0 | F5: 0 | G5: 0 | H5: =B{r}+F{r}+G{r} | I5: 0 | J5: =H{r}+I{r} | K5: =-Initial
A6: 1 | B6: =C6+D6 | C6: =H5 | D6: =Monthly | E6: =B6*Yield_m | F6: =IF(Reinvest="Sim",E6,0) | G6: =(B6+F6)*Growth_m | H6: =B6+F6+G6 | I6: =I5+(E6-F6) | J6: =H6+I6 | K6: =(E6-F6)-D6+IF(A6=Horizon,H6,0)
A7: 2 | B7: =C7+D7 | C7: =H6 | D7: =Monthly | E7: =B7*Yield_m | F7: =IF(Reinvest="Sim",E7,0) | G7: =(B7+F7)*Growth_m | H7: =B7+F7+G7 | I7: =I6+(E7-F7) | J7: =H7+I7 | K7: =(E7-F7)-D7+IF(A7=Horizon,H7,0)
A8: 3 | B8: =C8+D8 | C8: =H7 | D8: =Monthly | E8: =B8*Yield_m | F8: =IF(Reinvest="Sim",E8,0) | G8: =(B8+F8)*Growth_m | H8: =B8+F8+G8 | I8: =I7+(E8-F8) | J8: =H8+I8 | K8: =(E8-F8)-D8+IF(A8=Horizon,H8,0)
A9: 4 | B9: =C9+D9 | C9: =H8 | D9: =Monthly | E9: =B9*Yield_m | F9: =IF(Reinvest="Sim",E9,0) | G9: =(B9+F9)*Growth_m | H9: =B9+F9+G9 | I9: =I8+(E9-F9) | J9: =H9+I9 | K9: =(E9-F9)-D9+IF(A9=Horizon,H9,0)
A10: 5 | B10: =C10+D10 | C10: =H9 | D10: =Monthly | E10: =B10*Yield_m | F10: =IF(Reinvest="Sim",E10,0) | G10: =(B10+F10)*Growth_m | H10: =B10+F10+G10 | I10: =I9+(E10-F10) | J10: =H10+I10 | K10: =(E10-F10)-D10+IF(A10=Horizon,H10,0)
A11: 6 | B11: =C11+D11 | C11: =H10 | D11: =Monthly | E11: =B11*Yield_m | F11: =IF(Reinvest="Sim",E11,0) | G11: =(B11+F11)*Growth_m | H11: =B11+F11+G11 | I11: =I10+(E11-F11) | J11: =H11+I11 | K11: =(E11-F11)-D11+IF(A11=Horizon,H11,0)
A12: 7 | B12: =C12+D12 | C12: =H11 | D12: =Monthly | E12: =B12*Yield_m | F12: =IF(Reinvest="Sim",E12,0) | G12: =(B12+F12)*Growth_m | H12: =B12+F12+G12 | I12: =I11+(E12-F12) | J12: =H12+I12 | K12: =(E12-F12)-D12+IF(A12=Horizon,H12,0)
A13: 8 | B13: =C13+D13 | C13: =H12 | D13: =Monthly | E13: =B13*Yield_m | F13: =IF(Reinvest="Sim",E13,0) | G13: =(B13+F13)*Growth_m | H13: =B13+F13+G13 | I13: =I12+(E13-F13) | J13: =H13+I13 | K13: =(E13-F13)-D13+IF(A13=Horizon,H13,0)
A14: 9 | B14: =C14+D14 | C14: =H13 | D14: =Monthly | E14: =B14*Yield_m | F14: =IF(Reinvest="Sim",E14,0) | G14: =(B14+F14)*Growth_m | H14: =B14+F14+G14 | I14: =I13+(E14-F14) | J14: =H14+I14 | K14: =(E14-F14)-D14+IF(A14=Horizon,H14,0)
A15: 10 | B15: =C15+D15 | C15: =H14 | D15: =Monthly | E15: =B15*Yield_m | F15: =IF(Reinvest="Sim",E15,0) | G15: =(B15+F15)*Growth_m | H15: =B15+F15+G15 | I15: =I14+(E15-F15) | J15: =H15+I15 | K15: =(E15-F15)-D15+IF(A15=Horizon,H15,0)
A16: 11 | B16: =C16+D16 | C16: =H15 | D16: =Monthly | E16: =B16*Yield_m | F16: =IF(Reinvest="Sim",E16,0) | G16: =(B16+F16)*Growth_m | H16: =B16+F16+G16 | I16: =I15+(E16-F16) | J16: =H16+I16 | K16: =(E16-F16)-D16+IF(A16=Horizon,H16,0)
A17: 12 | B17: =C17+D17 | C17: =H16 | D17: =Monthly | E17: =B17*Yield_m | F17: =IF(Reinvest="Sim",E17,0) | G17: =(B17+F17)*Growth_m | H17: =B17+F17+G17 | I17: =I16+(E17-F17) | J17: =H17+I17 | K17: =(E17-F17)-D17+IF(A17=Horizon,H17,0)
... A365: 360 | B365: =C365+D365 | C365: =H364 | D365: =Monthly | E365: =B365*Yield_m | F365: =IF(Reinvest="Sim",E365,0) | G365: =(B365+F365)*Growth_m | H365: =B365+F365+G365 | I365: =I364+(E365-F365) | J365: =H365+I365 | K365: =(E365-F365)-D365+IF(A365=Horizon,H365,0)

Sheet DASH
B2: DASHBOARD EXECUTIVO
B7: KPIs (prazo selecionado em APP)
B8: Patrimônio Final | C8: =APP!K11 | F8: Total Investido | G8: =APP!K10 | J8: TIR anualizada | K8: =APP!K18
B9: Dividendos (último mês) | C9: =APP!K12 | F9: Riqueza Total Final | G9: =APP!K14 | J9: Patrimônio Real | K9: =APP!K19
B12: EVOLUÇÃO DO PATRIMÔNIO (BASE) | G12: EVOLUÇÃO DOS DIVIDENDOS (BASE)
B30: COMPARAÇÃO DE CENÁRIOS (NO PRAZO SELECIONADO)
B31: Cenário | C31: Taxa efetiva (mensal) | E31: Patrimônio Final | G31: Dividendo (último mês)
B32: Conservador | C32: =IF(Reinvest="Sim", (1+(Growth_m-DeltaGrowth))*(1+(MAX(0,Yield_m-DeltaYield)))-1, (Growth_m-DeltaGrowth)) | E32: =FV(C32, Horizon, -Monthly, -Initial, 0) | G32: =E32*(MAX(0,Yield_m-DeltaYield))
B33: Base | C33: =IF(Reinvest="Sim", (1+(Growth_m))*(1+(Yield_m))-1, (Growth_m)) | E33: =FV(C33, Horizon, -Monthly, -Initial, 0) | G33: =E33*(Yield_m)
B34: Agressivo | C34: =IF(Reinvest="Sim", (1+(Growth_m+DeltaGrowth))*(1+(Yield_m+DeltaYield))-1, (Growth_m+DeltaGrowth)) | E34: =FV(C34, Horizon, -Monthly, -Initial, 0) | G34: =E34*(Yield_m+DeltaYield)
